{
    "Titulo": "Partidas desde Jujuy",
    "Fecha_Modificacion": "20/04/2024 10:10",
    "Datos": [
        {
            "Hora": "07:45",
            "Vuelo": "AR 1513",
            "Linea Aerea": "Aerolineas Argentinas",
            "Ciudad": "Aeroparque",
            "Estima": "",
            "Terminal": "P",
            "Estado": "Despegado (08:25)"
        },
        {
            "Hora": "08:30",
            "Vuelo": "FO 5193",
            "Linea Aerea": "Flybondi",
            "Ciudad": "Aeroparque",
            "Estima": "",
            "Terminal": "P",
            "Estado": "Despegado (08:45)"
        },
        {
            "Hora": "19:55",
            "Vuelo": "AR 1519",
            "Linea Aerea": "Aerolineas Argentinas",
            "Ciudad": "Aeroparque",
            "Estima": "",
            "Terminal": "P",
            "Estado": "En Horario"
        },
        {
            "Hora": "20:46",
            "Vuelo": "WJ 3251",
            "Linea Aerea": "Jet Smart",
            "Ciudad": "Aeroparque",
            "Estima": "",
            "Terminal": "P",
            "Estado": "En Horario"
        },
        {
            "Hora": "21:50",
            "Vuelo": "FO 5197",
            "Linea Aerea": "Flybondi",
            "Ciudad": "Ezeiza",
            "Estima": "",
            "Terminal": "P",
            "Estado": "En Horario"
        }
    ]
}